LICENSE.txt
MANIFEST.in
README.md
setup.cfg
setup.py
src/decision_boundary_mapper/__init__.py
src/decision_boundary_mapper.egg-info/PKG-INFO
src/decision_boundary_mapper.egg-info/SOURCES.txt
src/decision_boundary_mapper.egg-info/dependency_links.txt
src/decision_boundary_mapper.egg-info/requires.txt
src/decision_boundary_mapper.egg-info/top_level.txt
src/decision_boundary_mapper/DBM/AbstractDBM.py
src/decision_boundary_mapper/DBM/AbstractNN.py
src/decision_boundary_mapper/DBM/__init__.py
src/decision_boundary_mapper/DBM/tools.py
src/decision_boundary_mapper/DBM/DBM/DBM.py
src/decision_boundary_mapper/DBM/DBM/NNInv.py
src/decision_boundary_mapper/DBM/DBM/__init__.py
src/decision_boundary_mapper/DBM/DBM/projections.py
src/decision_boundary_mapper/DBM/SDBM/Autoencoder.py
src/decision_boundary_mapper/DBM/SDBM/SDBM.py
src/decision_boundary_mapper/DBM/SDBM/SSNP.py
src/decision_boundary_mapper/DBM/SDBM/__init__.py
src/decision_boundary_mapper/GUI/DBMPlotterController.py
src/decision_boundary_mapper/GUI/DBMPlotterGUI.py
src/decision_boundary_mapper/GUI/GUI.py
src/decision_boundary_mapper/GUI/GUIController.py
src/decision_boundary_mapper/GUI/__init__.py
src/decision_boundary_mapper/GUI/utils.py
src/decision_boundary_mapper/GUI/assets/dbm_plotter_icon.png
src/decision_boundary_mapper/GUI/assets/dbm_plotter_icon_b64.txt
src/decision_boundary_mapper/GUI/assets/main_icon.png
src/decision_boundary_mapper/GUI/assets/main_icon_b64.txt
src/decision_boundary_mapper/GUI/assets/warning-sound.mp3
src/decision_boundary_mapper/Logger/Logger.py
src/decision_boundary_mapper/Logger/LoggerGUI.py
src/decision_boundary_mapper/Logger/LoggerInterface.py
src/decision_boundary_mapper/Logger/LoggerModel.py
src/decision_boundary_mapper/Logger/__init__.py
src/decision_boundary_mapper/examples/DBM_usage_example.py
src/decision_boundary_mapper/examples/SDBM_usage_example.py
src/decision_boundary_mapper/examples/__init__.py
src/decision_boundary_mapper/examples/utils.py
src/decision_boundary_mapper/utils/__init__.py
src/decision_boundary_mapper/utils/config.py
src/decision_boundary_mapper/utils/dataReader.py
src/decision_boundary_mapper/utils/tools.py