Metadata-Version: 2.1
Name: decision-boundary-mapper
Version: 0.7.6
Summary: A tool for visualizing the decision boundary of a machine learning model.
Home-page: https://github.com/cristi2019255/MasterThesis2023
Author: Cristian Grosu
Author-email: c.grosu@students.uu.nl
License: MIT
Keywords: Decision Boundary Mapper
Platform: UNKNOWN
